aur_info.py
aur_info-0.2.4.dist-info/LICENSE
aur_info-0.2.4.dist-info/METADATA
aur_info-0.2.4.dist-info/WHEEL
aur_info-0.2.4.dist-info/top_level.txt
aur_info-0.2.4.dist-info/RECORD
