Metadata-Version: 2.1
Name: aur-info
Version: 0.2.4
Summary: Retrieve package info from Arch User Repository (AUR).
Home-page: https://www.techtum.dev
Author: siphr
Author-email: pypi@techtum.dev
License: UNKNOWN
Project-URL: Bug Tracker, https://github.com/siphr/aur-info
Platform: UNKNOWN
Classifier: Programming Language :: Python :: 3
Classifier: License :: OSI Approved :: MIT License
Classifier: Operating System :: OS Independent
Requires-Python: >=3.6
License-File: LICENSE
